pycoinbase/__init__.py
pycoinbase/wallet/__init__.py
pycoinbase/wallet/auth.py
pycoinbase/wallet/client.py
pycoinbase/wallet/compat.py
pycoinbase/wallet/error.py
pycoinbase/wallet/model.py
pycoinbase/wallet/util.py
pycoinbase-2.1.3.dist-info/LICENSE
pycoinbase-2.1.3.dist-info/METADATA
pycoinbase-2.1.3.dist-info/WHEEL
pycoinbase-2.1.3.dist-info/top_level.txt
pycoinbase-2.1.3.dist-info/RECORD
