Metadata-Version: 2.1
Name: pycoinbase
Version: 2.1.3
Summary: Updated Coinbase API client library
Home-page: https://github.com/anton-stefanovich/pycoinbase/
Author: Anton Stefanovich
Author-email: UNKNOWN
License: Apache 2.0
Keywords: api,coinbase,bitcoin,oauth2,client
Platform: UNKNOWN
Classifier: Intended Audience :: Developers
Classifier: License :: OSI Approved :: MIT License
Classifier: Operating System :: OS Independent
Classifier: Programming Language :: Python :: 2
Classifier: Programming Language :: Python :: 2.7
Classifier: Programming Language :: Python :: 3
Classifier: Programming Language :: Python :: 3.4
Classifier: Programming Language :: Python :: 3.5
Classifier: Programming Language :: Python :: 3.6
Classifier: Programming Language :: Python :: 3.7
Classifier: Programming Language :: Python :: 3.8
Classifier: Programming Language :: Python
Classifier: Topic :: Software Development :: Libraries :: Python Modules
Requires-Dist: requests (>=2.5)
Requires-Dist: six (>=1.9)
Requires-Dist: pycryptodome (>=3.4.11)
